Metadata-Version: 1.2
Name: toggl-client
Version: 0.1.1
Summary: Cliente para a toggl API
Home-page: https://github.com/lramosduarte/toggl-client
Author: Leonardo Ramos Duarte
Author-email: lramosduarte@gmail.com
License: MIT
Keywords: toggl toggl-api toggl-client
Platform: UNKNOWN
Classifier: Development Status :: 4 - Beta
Classifier: Intended Audience :: Developers
Classifier: License :: OSI Approved :: MIT License
Classifier: Programming Language :: Python :: 3
Requires-Python: >=3
